timeseriesql/__init__.py
timeseriesql/ast.py
timeseriesql/decompiler.py
timeseriesql/np_array.py
timeseriesql/plot.py
timeseriesql/query.py
timeseriesql/time.py
timeseriesql/time_chunk.py
timeseriesql/timeseries.py
timeseriesql/timeseries_collection.py
timeseriesql/backends/ao_backend.py
timeseriesql/backends/csv_backend.py
timeseriesql/data/README.rst
timeseriesql/tests/__init__.py
timeseriesql/tests/ast_test.py
timeseriesql/tests/csv_backend_test.py
timeseriesql/tests/query_test.py
timeseriesql/tests/timeseries_test.py
timeseriesql/utils/__init__.py
timeseriesql-0.1.6.dist-info/METADATA
timeseriesql-0.1.6.dist-info/WHEEL
timeseriesql-0.1.6.dist-info/top_level.txt
timeseriesql-0.1.6.dist-info/RECORD
