Metadata-Version: 2.1
Name: timeseriesql
Version: 0.1.6
Summary: A Pythonic query language for time series data
Home-page: http://github.com/mbeale/timeseriesql
Author: Michael Beale
Author-email: michael.beale@gmail.com
License: MIT
Platform: UNKNOWN
Classifier: Programming Language :: Python :: 3
Classifier: License :: OSI Approved :: MIT License
Classifier: Operating System :: OS Independent
Classifier: Development Status :: 3 - Alpha
Requires-Python: >=3.6
Requires-Dist: numpy
Requires-Dist: python-dateutil
